{
  "name": "userIdentity",
  "plural": "userIdentities",
  "base": "UserIdentity",
  "mixins": {
    "TimeStamp": {
      "createdAt": "createdAt",
      "updatedAt": "updatedAt",
      "required": false
    },
    "GlobalUtils": {}
  },
  "properties": {
    "provider": {
      "type": "string"
    },
    "externalId": {
      "type": "string"
    },
    "authScheme": {
      "type": "string"
    },
    "profile": {
      "type": "string"
    },
    "credentials": {
      "type": "string"
    },
    "userId": {
      "type": "string"
    }
  },
  "validations": [],
  "relations": {
    "peer": {
      "type": "belongsTo",
      "model": "peer",
      "foreignKey": "targetId",
      "through": "peer_has_identity",
      "keyThrough": "sourceId"
    }
  },
  "acls": [],
  "methods": {}
}
