{
  "name": "peer_has_collection",
  "base": "PersistedModel",
  "idInjection": true,
  "options": {
    "validateUpsert": true
  },
  "neo4j": {
    "sourceModel": "peer",
    "targetModel": "collection"
  },
  "properties": {
    "id": {
      "type": "string",
      "id": true
    },
    "sourceId": {
      "type": "string"
    },
    "targetId": {
      "type": "string"
    }
  },
  "validations": [],
  "relations": {
    "peer": {
      "type": "belongsTo",
      "model": "peer",
      "foreignKey": "sourceId"
    },
    "collection": {
      "type": "belongsTo",
      "model": "collection",
      "foreignKey": "targetId"
    }
  },
  "acls": [],
  "methods": {}
}
